matrix_ops
