Metadata-Version: 1.0
Name: matrix-ops
Version: 1.5
Summary: Martix Operations
Home-page: UNKNOWN
Author: UNKNOWN
Author-email: UNKNOWN
License: UNKNOWN
Platform: UNKNOWN
